{
  "schema_version": "2026-07-01",
  "name": "libidn2/libidn2",
  "version": "2.3.7",
  "description": "PHP FFI wrapper for libidn2 IDNA handling.",
  "authors": [
    {
      "name": "libidn2 maintainers"
    }
  ],
  "license": "LGPL-3.0-or-later",
  "entrypoint": "src/generated/index.php",
  "class": "Pnlx\\Libidn2\\Libidn2",
  "examples": [
    "use Pnlx\\Libidn2\\Libidn2;\nuse Pnlx\\Runtime;\nuse function Pnlx\\Util\\is_null;\n\n$runtime = new Runtime(__DIR__);\n$libidn2 = $runtime->load(Libidn2::class);\n\n// Check library version\n$version = $libidn2->idn2_check_version('2.0.0');\necho \"libidn2 version >= 2.0.0: \" . ($version !== null ? $version : 'no') . \"\\n\";\n\n// Convert an internationalized domain name to ACE (ASCII-compatible encoding)\n$output = $runtime->allocator()->make(\\Pnlx\\FFI\\AllocationType::VoidPointer);\n$rc = $libidn2->idn2_lookup_u8('www.b\\u00fccher.example', $output, 0);\nif ($rc === 0) {\n    echo \"ACE label: \" . $output[0] . \"\\n\";\n    $libidn2->idn2_free($output[0]);\n}"
  ],
  "platforms": [
    {
      "os": "darwin",
      "arch": "aarch64"
    },
    {
      "os": "darwin",
      "arch": "x86_64"
    },
    {
      "os": "linux",
      "arch": "x86_64"
    },
    {
      "os": "linux",
      "arch": "aarch64"
    },
    {
      "os": "windows",
      "arch": "x86_64"
    }
  ],
  "requires": {
    "libidn2": {
      "symbol_prefix": "idn2",
      "library_names": [
        "libidn2.dylib",
        "libidn2.so",
        "idn2.dll"
      ],
      "header_names": [
        "idn2.h"
      ],
      "version": ">=2.0.0 & <3.0.0",
      "required": true
    }
  },
  "dependencies": {}
}
