{
  "schema_version": "2026-07-01",
  "name": "libopus/libopus",
  "version": "1.5.2",
  "description": "PHP FFI wrapper for the Opus audio codec.",
  "authors": [
    {
      "name": "Opus maintainers"
    }
  ],
  "license": "BSD-3-Clause",
  "entrypoint": "src/generated/index.php",
  "class": "Pnlx\\Libopus\\Libopus",
  "examples": [
    "use Pnlx\\Libopus\\Libopus;\nuse Pnlx\\Runtime;\nuse function Pnlx\\Util\\is_null;\n\n$runtime = new Runtime(__DIR__);\n$libopus = $runtime->load(Libopus::class);\n\n// Query the library version string (char* → PHP string)\n$version = $libopus->opus_get_version_string();\necho \"Opus version: $version\\n\";\n\n// Create an encoder: 48 kHz, 2 channels, OPUS_APPLICATION_AUDIO = 2049\n$error = $runtime->allocator()->make(\\Pnlx\\FFI\\AllocationType::Int);\n$encoder = $libopus->opus_encoder_create(48000, 2, 2049, $error);\nif (is_null($encoder)) {\n    echo \"Encoder error: \" . $error->cdata . \"\\n\";\n} else {\n    // ... encode PCM frames with opus_encode() ...\n    $libopus->opus_encoder_destroy($encoder);\n}"
  ],
  "installation": {
    "darwin": {
      "install": ["brew install opus"],
      "checkIfExists": ["brew list opus"]
    },
    "linux": {
      "install": ["sudo apt-get install -y libopus-dev"],
      "checkIfExists": ["pkg-config --exists opus"]
    }
  },
  "platforms": [
    {
      "os": "darwin",
      "arch": "aarch64"
    },
    {
      "os": "darwin",
      "arch": "x86_64"
    },
    {
      "os": "linux",
      "arch": "x86_64"
    },
    {
      "os": "linux",
      "arch": "aarch64"
    },
    {
      "os": "windows",
      "arch": "x86_64"
    }
  ],
  "requires": {
    "opus": {
      "symbol_prefix": "opus",
      "library_names": [
        "libopus.dylib",
        "libopus.so",
        "opus.dll"
      ],
      "header_names": [
        "opus/opus.h"
      ],
      "version": ">=1.3.0 & <2.0.0",
      "required": true
    }
  },
  "dependencies": {}
}
